[
  {
    "id": "5.001",
    "text": "komunikace která nepotřebuje porozumění potlačený vztek s reklamním logem moje chyba že je nevidím",
    "type": "sociálně-psychologický",
    "function": "zkoumá prázdnou komunikaci a potlačené emoce maskované reklamou",
    "fields": ["komunikace", "porozumění", "vztek", "reklama"],
    "movement": "povrch → skrytost",
    "intensity": "střední",
    "language": "cs",
    "version": "1.0",
    "created": "2025-01-16",
    "source": "[Semantic Gap Generative Dataset v5.0 – Fenomény / Situace / Kurátor] od Michaela Nováková"
  },
  {
    "id": "5.002",
    "text": "beat z bublin kašel místo plemene chyby nejsou tak je nehledej",
    "type": "surrealisticko-existenciální",
    "function": "propojuje prchavost bublin s tělesným projevem a popíráním chyb",
    "fields": ["beat", "bubliny", "kašel", "chyby"],
    "movement": "prchavost → popření",
    "intensity": "střední",
    "language": "cs",
    "version": "1.0",
    "created": "2025-01-16",
    "source": "[Semantic Gap Generative Dataset v5.0 – Fenomény / Situace / Kurátor] od Michaela Nováková"
  },
  {
    "id": "5.003",
    "text": "hodnota věcí se mění s osvětlením vlčí doktor bez očních stínů ego jako paleta se špatným krytím",
    "type": "esteticko-psychologický",
    "function": "zkoumá relativitu hodnot a nedokonalost ega",
    "fields": ["hodnota", "osvětlení", "doktor", "ego"],
    "movement": "proměna → nedokonalost",
    "intensity": "vysoká",
    "language": "cs",
    "version": "1.0",
    "created": "2025-01-16",
    "source": "[Semantic Gap Generative Dataset v5.0 – Fenomény / Situace / Kurátor] od Michaela Nováková"
  },
  {
    "id": "5.004",
    "text": "mam verzi sebe kterou ukazuji jenom nocím archetyp léčitele s ostrými zuby reklama na identitu v černobílém světě",
    "type": "introspektivně-sociální",
    "function": "zkoumá noční identitu a reklamu na sebe v redukovaném světě",
    "fields": ["verze", "noc", "archetyp", "reklama"],
    "movement": "skrytost → prezentace",
    "intensity": "vysoká",
    "language": "cs",
    "version": "1.0",
    "created": "2025-01-16",
    "source": "[Semantic Gap Generative Dataset v5.0 – Fenomény / Situace / Kurátor] od Michaela Nováková"
  },
  {
    "id": "5.005",
    "text": "identita jako transformace podstata nezávislá na prostředí dívám se na sebe abych si byl jistý že existuji",
    "type": "filosoficko-existenciální",
    "function": "zkoumá identitu v pohybu a potřebu sebe-pozorování pro existenci",
    "fields": ["identita", "transformace", "podstata", "existence"],
    "movement": "proměna → jistota",
    "intensity": "střední",
    "language": "cs",
    "version": "1.0",
    "created": "2025-01-16",
    "source": "[Semantic Gap Generative Dataset v5.0 – Fenomény / Situace / Kurátor] od Michaela Nováková"
  },
  {
    "id": "5.006",
    "text": "žádný oheň nepálí stejně potřeba být viděn i když už se díváme sny které definují",
    "type": "existenciálně-snový",
    "function": "zkoumá jedinečnost prožitku a potřebu uznání skrze sny",
    "fields": ["oheň", "vidění", "sny", "definice"],
    "movement": "jedinečnost → definice",
    "intensity": "střední",
    "language": "cs",
    "version": "1.0",
    "created": "2025-01-16",
    "source": "[Semantic Gap Generative Dataset v5.0 – Fenomény / Situace / Kurátor] od Michaela Nováková"
  },
  {
    "id": "5.007",
    "text": "zmražený okamžik zlo jako vedlejší produkt světla kdo se stane kým?",
    "type": "metafyzicko-etický",
    "function": "zkoumá zamrzlý čas a zlo jako důsledek světla",
    "fields": ["okamžik", "zlo", "světlo", "identita"],
    "movement": "zastavení → otázka",
    "intensity": "vysoká",
    "language": "cs",
    "version": "1.0",
    "created": "2025-01-16",
    "source": "[Semantic Gap Generative Dataset v5.0 – Fenomény / Situace / Kurátor] od Michaela Nováková"
  },
  {
    "id": "5.008",
    "text": "viditelná nenápadnost osvícení ztrátou původu zvířecí metafora dětství",
    "type": "psychologicko-mytologický",
    "function": "zkoumá paradox viditelné nenápadnosti a ztrátu původu",
    "fields": ["nenápadnost", "osvícení", "původ", "dětství"],
    "movement": "viditelnost → ztráta",
    "intensity": "střední",
    "language": "cs",
    "version": "1.0",
    "created": "2025-01-16",
    "source": "[Semantic Gap Generative Dataset v5.0 – Fenomény / Situace / Kurátor] od Michaela Nováková"
  },
  {
    "id": "5.009",
    "text": "perfekcionismus s opičím ocasem nepřestupek je vnímán jako hrozba hudba bez plic",
    "type": "psychologicko-sociální",
    "function": "zkoumá absurdní perfekcionismus a vnímání neviny jako hrozby",
    "fields": ["perfekcionismus", "nepřestupek", "hrozba", "hudba"],
    "movement": "dokonalost → ohrožení",
    "intensity": "vysoká",
    "language": "cs",
    "version": "1.0",
    "created": "2025-01-16",
    "source": "[Semantic Gap Generative Dataset v5.0 – Fenomény / Situace / Kurátor] od Michaela Nováková"
  },
  {
    "id": "5.010",
    "text": "hlas podvědomí slepec pravdy kašel co vypráví příběh",
    "type": "psychologicko-narativní",
    "function": "propojuje podvědomí, slepotu k pravdě a tělesný příběh",
    "fields": ["hlas", "podvědomí", "pravda", "kašel"],
    "movement": "nevědomí → projev",
    "intensity": "střední",
    "language": "cs",
    "version": "1.0",
    "created": "2025-01-16",
    "source": "[Semantic Gap Generative Dataset v5.0 – Fenomény / Situace / Kurátor] od Michaela Nováková"
  },
  {
    "id": "5.011",
    "text": "estetická diagnóza ega pomoc kterou nepoznáš když jsi hladový část osobnosti která funguje jen beze svědků",
    "type": "psychologicko-sociální",
    "function": "diagnostikuje ego a zkoumá skryté části osobnosti",
    "fields": ["ego", "diagnóza", "pomoc", "osobnost"],
    "movement": "diagnóza → skrytost",
    "intensity": "vysoká",
    "language": "cs",
    "version": "1.0",
    "created": "2025-01-16",
    "source": "[Semantic Gap Generative Dataset v5.0 – Fenomény / Situace / Kurátor] od Michaela Nováková"
  },
  {
    "id": "5.012",
    "text": "Disneyho bastard sebevědomí pomáhám i těm co mě sežerou estetika outsiderů",
    "type": "sociálně-kritický",
    "function": "kritizuje hybridní sebevědomí a estetiku outsiderů",
    "fields": ["sebevědomí", "pomoc", "predace", "outsider"],
    "movement": "hybrid → sebedestrukce",
    "intensity": "vysoká",
    "language": "cs",
    "version": "1.0",
    "created": "2025-01-16",
    "source": "[Semantic Gap Generative Dataset v5.0 – Fenomény / Situace / Kurátor] od Michaela Nováková"
  },
  {
    "id": "5.013",
    "text": "estetika přebytku přesnost tam kde na ní nezáleží drak kašle a lidé křičí",
    "type": "esteticko-surrealistický",
    "function": "kritizuje estetiku přebytku a absurditu draka",
    "fields": ["estetika", "přebytek", "přesnost", "drak"],
    "movement": "přebytek → chaos",
    "intensity": "vysoká",
    "language": "cs",
    "version": "1.0",
    "created": "2025-01-16",
    "source": "[Semantic Gap Generative Dataset v5.0 – Fenomény / Situace / Kurátor] od Michaela Nováková"
  },
  {
    "id": "5.014",
    "text": "soutěž pohledů bez poroty trávení interpunkce zvuk jako porušení pravidel",
    "type": "sociálně-lingvistický",
    "function": "zkoumá soutěživost pohledů a jazyk jako pravidla",
    "fields": ["soutěž", "pohledy", "interpunkce", "zvuk"],
    "movement": "soutěž → porušení",
    "intensity": "střední",
    "language": "cs",
    "version": "1.0",
    "created": "2025-01-16",
    "source": "[Semantic Gap Generative Dataset v5.0 – Fenomény / Situace / Kurátor] od Michaela Nováková"
  },
  {
    "id": "5.015",
    "text": "překvapení z předvídatelného moralita v převleku za evoluci věta která ruší všechny ostatní",
    "type": "eticko-lingvistický",
    "function": "zkoumá paradox překvapení a morálku maskovanou jako evoluci",
    "fields": ["překvapení", "moralita", "evoluce", "věta"],
    "movement": "očekávání → zrušení",
    "intensity": "vysoká",
    "language": "cs",
    "version": "1.0",
    "created": "2025-01-16",
    "source": "[Semantic Gap Generative Dataset v5.0 – Fenomény / Situace / Kurátor] od Michaela Nováková"
  },
  {
    "id": "5.016",
    "text": "role která mění vlastní formu věta která se svíjí jako to o čem mluví kontrast k výkonu",
    "type": "performativně-lingvistický",
    "function": "zkoumá proměnlivost rolí a sebe-referenční jazyk",
    "fields": ["role", "forma", "věta", "výkon"],
    "movement": "proměna → kontrast",
    "intensity": "vysoká",
    "language": "cs",
    "version": "1.0",
    "created": "2025-01-16",
    "source": "[Semantic Gap Generative Dataset v5.0 – Fenomény / Situace / Kurátor] od Michaela Nováková"
  },
  {
    "id": "5.017",
    "text": "stereotyp naruby redundance jako ornament Lucifer v krajice",
    "type": "kulturně-surrealistický",
    "function": "obrací stereotypy a propojuje redundanci s Luciferem",
    "fields": ["stereotyp", "redundance", "ornament", "lucifer"],
    "movement": "obrat → absurdita",
    "intensity": "vysoká",
    "language": "cs",
    "version": "1.0",
    "created": "2025-01-16",
    "source": "[Semantic Gap Generative Dataset v5.0 – Fenomény / Situace / Kurátor] od Michaela Nováková"
  },
  {
    "id": "5.018",
    "text": "okázalost která sleduje sama sebe zajíc není palivo moralita v převleku za evoluci",
    "type": "eticko-ekologický",
    "function": "kritizuje sebestřednost a morálku jako masku",
    "fields": ["okázalost", "zajíc", "moralita", "evoluce"],
    "movement": "sebestřednost → maska",
    "intensity": "vysoká",
    "language": "cs",
    "version": "1.0",
    "created": "2025-01-16",
    "source": "[Semantic Gap Generative Dataset v5.0 – Fenomény / Situace / Kurátor] od Michaela Nováková"
  },
  {
    "id": "5.019",
    "text": "charita jako lovestory kašel místo plemene negace přísloví",
    "type": "sociálně-lingvistický",
    "function": "zkoumá charitu jako romanci a negaci moudrosti",
    "fields": ["charita", "příběh", "kašel", "přísloví"],
    "movement": "idealizace → negace",
    "intensity": "střední",
    "language": "cs",
    "version": "1.0",
    "created": "2025-01-16",
    "source": "[Semantic Gap Generative Dataset v5.0 – Fenomény / Situace / Kurátor] od Michaela Nováková"
  },
  {
    "id": "5.020",
    "text": "myslel že je to značka jídla touha po moci a síle kašel je jen přerušené slovo",
    "type": "psychologicko-lingvistický",
    "function": "zkoumá záměnu symbolů a kašel jako přerušenou řeč",
    "fields": ["značka", "moc", "kašel", "slovo"],
    "movement": "omyl → přerušení",
    "intensity": "střední",
    "language": "cs",
    "version": "1.0",
    "created": "2025-01-16",
    "source": "[Semantic Gap Generative Dataset v5.0 – Fenomény / Situace / Kurátor] od Michaela Nováková"
  },
  {
    "id": "5.021",
    "text": "dokonalost jako psychóza kontrast k výkonu noční tvář já",
    "type": "psychologicko-existenciální",
    "function": "zkoumá dokonalost jako šílenství a noční identitu",
    "fields": ["dokonalost", "psychóza", "výkon", "noc"],
    "movement": "ideál → stín",
    "intensity": "vysoká",
    "language": "cs",
    "version": "1.0",
    "created": "2025-01-16",
    "source": "[Semantic Gap Generative Dataset v5.0 – Fenomény / Situace / Kurátor] od Michaela Nováková"
  },
  {
    "id": "5.022",
    "text": "kdo nevidí chyby má špatný zrak - nebo pravdu pozorovatel prahu glamour s blánami",
    "type": "epistemologicko-estetický",
    "function": "zkoumá vidění chyb a pravdu na prahu",
    "fields": ["chyby", "zrak", "pravda", "glamour"],
    "movement": "vidění → pravda",
    "intensity": "střední",
    "language": "cs",
    "version": "1.0",
    "created": "2025-01-16",
    "source": "[Semantic Gap Generative Dataset v5.0 – Fenomény / Situace / Kurátor] od Michaela Nováková"
  },
  {
    "id": "5.023",
    "text": "konzument smyslu barvy které neexistují ale štěkají rytmus místo slov",
    "type": "sémanticko-percepční",
    "function": "zkoumá konzumaci smyslu a neexistující vjemy",
    "fields": ["smysl", "barvy", "rytmus", "slova"],
    "movement": "konzumace → abstrakce",
    "intensity": "vysoká",
    "language": "cs",
    "version": "1.0",
    "created": "2025-01-16",
    "source": "[Semantic Gap Generative Dataset v5.0 – Fenomény / Situace / Kurátor] od Michaela Nováková"
  },
  {
    "id": "5.024",
    "text": "svědomí v dávkách odlišnost jako důkaz života hudba bez plic",
    "type": "eticko-biologický",
    "function": "zkoumá dávkované svědomí a odlišnost jako znak života",
    "fields": ["svědomí", "odlišnost", "život", "hudba"],
    "movement": "dávka → důkaz",
    "intensity": "střední",
    "language": "cs",
    "version": "1.0",
    "created": "2025-01-16",
    "source": "[Semantic Gap Generative Dataset v5.0 – Fenomény / Situace / Kurátor] od Michaela Nováková"
  },
  {
    "id": "5.025",
    "text": "Rajská zahrada v make-up tutoriálu oběť která nehoří narcismus s peřím",
    "type": "kulturně-psychologický",
    "function": "kritizuje komercializaci ráje a narcismus",
    "fields": ["ráj", "make-up", "oběť", "narcismus"],
    "movement": "ideál → povrch",
    "intensity": "vysoká",
    "language": "cs",
    "version": "1.0",
    "created": "2025-01-16",
    "source": "[Semantic Gap Generative Dataset v5.0 – Fenomény / Situace / Kurátor] od Michaela Nováková"
  },
  {
    "id": "5.026",
    "text": "vypadá roztomile dokud nepromluví legendou náhodou strážce obrazů já",
    "type": "sociálně-psychologický",
    "function": "zkoumá rozpor vzhledu a projevu a náhodnou legendu",
    "fields": ["vzhled", "řeč", "legenda", "já"],
    "movement": "povrch → hloubka",
    "intensity": "střední",
    "language": "cs",
    "version": "1.0",
    "created": "2025-01-16",
    "source": "[Semantic Gap Generative Dataset v5.0 – Fenomény / Situace / Kurátor] od Michaela Nováková"
  },
  {
    "id": "5.027",
    "text": "zvuk jako porušení pravidel každý má své sny humanita v rukou predátora",
    "type": "sociálně-politický",
    "function": "zkoumá zvuk jako narušení a lidskost v moci predátora",
    "fields": ["zvuk", "pravidla", "sny", "predátor"],
    "movement": "porušení → ohrožení",
    "intensity": "vysoká",
    "language": "cs",
    "version": "1.0",
    "created": "2025-01-16",
    "source": "[Semantic Gap Generative Dataset v5.0 – Fenomény / Situace / Kurátor] od Michaela Nováková"
  },
  {
    "id": "5.028",
    "text": "drak kašle a lidé křičí očekávání vs realita záchrana jako špatně přeložené slovo",
    "type": "surrealisticko-lingvistický",
    "function": "zkoumá absurditu draka a jazyk jako překlad",
    "fields": ["drak", "očekávání", "realita", "záchrana"],
    "movement": "mýtus → realita",
    "intensity": "vysoká",
    "language": "cs",
    "version": "1.0",
    "created": "2025-01-16",
    "source": "[Semantic Gap Generative Dataset v5.0 – Fenomény / Situace / Kurátor] od Michaela Nováková"
  },
  {
    "id": "5.029",
    "text": "přídavné jméno platné jen v noci nenápadnost křičící imperativ samocenzury",
    "type": "lingvisticko-psychologický",
    "function": "zkoumá noční jazyk a křiklavou nenápadnost cenzury",
    "fields": ["jazyk", "noc", "nenápadnost", "cenzura"],
    "movement": "noc → imperativ",
    "intensity": "střední",
    "language": "cs",
    "version": "1.0",
    "created": "2025-01-16",
    "source": "[Semantic Gap Generative Dataset v5.0 – Fenomény / Situace / Kurátor] od Michaela Nováková"
  },
  {
    "id": "5.030",
    "text": "ve tmě jsem hezčí aktivní pasivita obranný mechanismus ve formě sloganu",
    "type": "introspektivně-psychologický",
    "function": "zkoumá noční krásu a obranu skrze slogan",
    "fields": ["tma", "krása", "pasivita", "slogan"],
    "movement": "noc → obrana",
    "intensity": "střední",
    "language": "cs",
    "version": "1.0",
    "created": "2025-01-16",
    "source": "[Semantic Gap Generative Dataset v5.0 – Fenomény / Situace / Kurátor] od Michaela Nováková"
  },
  {
    "id": "5.031",
    "text": "projev slyšitelný jen pod hladinou chce být prostě jiná statistiky trávení",
    "type": "surrealisticko-biologický",
    "function": "zkoumá skrytý projev a touhu po jinakosti",
    "fields": ["projev", "hladina", "jinakost", "statistiky"],
    "movement": "skrytost → touha",
    "intensity": "střední",
    "language": "cs",
    "version": "1.0",
    "created": "2025-01-16",
    "source": "[Semantic Gap Generative Dataset v5.0 – Fenomény / Situace / Kurátor] od Michaela Nováková"
  },
  {
    "id": "5.032",
    "text": "rytmus místo slov ego jako paleta se špatným krytím náhoda která se tváří jako pravidlo",
    "type": "esteticko-epistemologický",
    "function": "zkoumá rytmus, nedokonalé ego a náhodu jako pravidlo",
    "fields": ["rytmus", "slova", "ego", "náhoda"],
    "movement": "abstrakce → řád",
    "intensity": "vysoká",
    "language": "cs",
    "version": "1.0",
    "created": "2025-01-16",
    "source": "[Semantic Gap Generative Dataset v5.0 – Fenomény / Situace / Kurátor] od Michaela Nováková"
  },
  {
    "id": "5.033",
    "text": "kašel co vypráví příběh elegance závislá na tmě čísla vycházející z tlamy",
    "type": "narativně-symbolický",
    "function": "propojuje tělesný příběh, noční eleganci a čísla",
    "fields": ["kašel", "příběh", "tma", "čísla"],
    "movement": "tělo → symbol",
    "intensity": "vysoká",
    "language": "cs",
    "version": "1.0",
    "created": "2025-01-16",
    "source": "[Semantic Gap Generative Dataset v5.0 – Fenomény / Situace / Kurátor] od Michaela Nováková"
  },
  {
    "id": "5.034",
    "text": "přestupek bez hříchu šperk který se rozpadne při svítání konzument smyslu",
    "type": "eticko-estetický",
    "function": "zkoumá přestupek bez viny a prchavou krásu",
    "fields": ["přestupek", "hřích", "šperk", "smysl"],
    "movement": "provinění → zánik",
    "intensity": "vysoká",
    "language": "cs",
    "version": "1.0",
    "created": "2025-01-16",
    "source": "[Semantic Gap Generative Dataset v5.0 – Fenomény / Situace / Kurátor] od Michaela Nováková"
  },
  {
    "id": "5.035",
    "text": "pozoroval prahu underground doslova etika bez barev",
    "type": "sociálně-etický",
    "function": "zkoumá hranici a etiku bez kategorie",
    "fields": ["práh", "underground", "etika", "barvy"],
    "movement": "hranice → šeď",
    "intensity": "nízká",
    "language": "cs",
    "version": "1.0",
    "created": "2025-01-16",
    "source": "[Semantic Gap Generative Dataset v5.0 – Fenomény / Situace / Kurátor] od Michaela Nováková"
  },
  {
    "id": "5.036",
    "text": "nečinnost jako strategie vnitřní monolog beze svědků empatie slepá pro rozdíl",
    "type": "psychologicko-sociální",
    "function": "zkoumá pasivitu jako taktiku a slepou empatii",
    "fields": ["nečinnost", "strategie", "monolog", "empatie"],
    "movement": "pasivita → slepota",
    "intensity": "střední",
    "language": "cs",
    "version": "1.0",
    "created": "2025-01-16",
    "source": "[Semantic Gap Generative Dataset v5.0 – Fenomény / Situace / Kurátor] od Michaela Nováková"
  },
  {
    "id": "5.037",
    "text": "klaun individuality anděl co zapomněl křídla ale nechal si jazyk oheň který nefunguje",
    "type": "surrealisticko-existenciální",
    "function": "zkoumá individualitu jako klaunství a nefunkční oheň",
    "fields": ["klaun", "anděl", "jazyk", "oheň"],
    "movement": "individualita → selhání",
    "intensity": "vysoká",
    "language": "cs",
    "version": "1.0",
    "created": "2025-01-16",
    "source": "[Semantic Gap Generative Dataset v5.0 – Fenomény / Situace / Kurátor] od Michaela Nováková"
  },
  {
    "id": "5.038",
    "text": "potřeba zazářit mezi skvrnami možná mám taky svůj hadí původ oběť která nehoří",
    "type": "psychologicko-mytologický",
    "function": "zkoumá potřebu vyniknout a hadí původ",
    "fields": ["záře", "skvrny", "had", "oběť"],
    "movement": "potřeba → původ",
    "intensity": "střední",
    "language": "cs",
    "version": "1.0",
    "created": "2025-01-16",
    "source": "[Semantic Gap Generative Dataset v5.0 – Fenomény / Situace / Kurátor] od Michaela Nováková"
  },
  {
    "id": "5.039",
    "text": "přání přiložené do symbolu kontrola kvality v krajině snu identita vznikla z nekonečného rozmnožují",
    "type": "snově-symbolický",
    "function": "zkoumá přání v symbolech a identitu z množení",
    "fields": ["přání", "symbol", "sen", "identita"],
    "movement": "přání → množení",
    "intensity": "vysoká",
    "language": "cs",
    "version": "1.0",
    "created": "2025-01-16",
    "source": "[Semantic Gap Generative Dataset v5.0 – Fenomény / Situace / Kurátor] od Michaela Nováková"
  },
  {
    "id": "5.040",
    "text": "každý má své sny perfekcionismus s opičím ocasem oči které se rozmnožují",
    "type": "psychologicko-surrealistický",
    "function": "propojuje sny, absurdní perfekcionismus a množení očí",
    "fields": ["sny", "perfekcionismus", "oči", "množení"],
    "movement": "sen → multiplicita",
    "intensity": "vysoká",
    "language": "cs",
    "version": "1.0",
    "created": "2025-01-16",
    "source": "[Semantic Gap Generative Dataset v5.0 – Fenomény / Situace / Kurátor] od Michaela Nováková"
  },
  {
    "id": "5.041",
    "text": "náhoda která se tváří jako pravidlo šperk který se rozpadne při svítání drak na detoxu",
    "type": "surrealisticko-symbolický",
    "function": "zkoumá náhodu jako řád a prchavost krásy",
    "fields": ["náhoda", "pravidlo", "šperk", "drak"],
    "movement": "řád → rozpad",
    "intensity": "vysoká",
    "language": "cs",
    "version": "1.0",
    "created": "2025-01-16",
    "source": "[Semantic Gap Generative Dataset v5.0 – Fenomény / Situace / Kurátor] od Michaela Nováková"
  },
  {
    "id": "5.042",
    "text": "tečka jako vedlejší produkt věty ve tmě jsem hezčí legenda v karanténě",
    "type": "lingvisticko-existenciální",
    "function": "zkoumá tečku jako produkt a noční legendu",
    "fields": ["tečka", "věta", "tma", "legenda"],
    "movement": "jazyk → izolace",
    "intensity": "střední",
    "language": "cs",
    "version": "1.0",
    "created": "2025-01-16",
    "source": "[Semantic Gap Generative Dataset v5.0 – Fenomény / Situace / Kurátor] od Michaela Nováková"
  },
  {
    "id": "5.043",
    "text": "symbol co ztratil červenou hlas podvědomí nemusím reagovat",
    "type": "psychologicko-symbolický",
    "function": "zkoumá ztrátu symbolu a pasivitu vůči podvědomí",
    "fields": ["symbol", "červená", "hlas", "reakce"],
    "movement": "ztráta → pasivita",
    "intensity": "střední",
    "language": "cs",
    "version": "1.0",
    "created": "2025-01-16",
    "source": "[Semantic Gap Generative Dataset v5.0 – Fenomény / Situace / Kurátor] od Michaela Nováková"
  },
  {
    "id": "5.044",
    "text": "vlčí doktor bez očních filtrů prostě to plyne úleva z nevolby",
    "type": "existenciálně-biologický",
    "function": "zkoumá syrovost pohledu a úlevu z nemožnosti volby",
    "fields": ["doktor", "filtry", "plynutí", "nevolba"],
    "movement": "syrovost → úleva",
    "intensity": "střední",
    "language": "cs",
    "version": "1.0",
    "created": "2025-01-16",
    "source": "[Semantic Gap Generative Dataset v5.0 – Fenomény / Situace / Kurátor] od Michaela Nováková"
  },
  {
    "id": "5.045",
    "text": "hrdinkou díky omylu nebeská chyba v živočišné výrobě srovnávací stupeň existence",
    "type": "eticko-existenciální",
    "function": "zkoumá hrdinství z omylu a existenci jako stupnici",
    "fields": ["hrdina", "omyl", "chyba", "existence"],
    "movement": "omyl → stupeň",
    "intensity": "vysoká",
    "language": "cs",
    "version": "1.0",
    "created": "2025-01-16",
    "source": "[Semantic Gap Generative Dataset v5.0 – Fenomény / Situace / Kurátor] od Michaela Nováková"
  },
  {
    "id": "5.046",
    "text": "každá moje barva je trochu lež, význam ticha mezi možnostmi, odolnost tam kde se čeká slabost",
    "type": "sebereflexivně-existenciální",
    "function": "zkoumá lež identity, ticho a neočekávanou odolnost",
    "fields": ["barva", "lež", "ticho", "odolnost"],
    "movement": "lež → odolnost",
    "intensity": "vysoká",
    "language": "cs",
    "version": "1.0",
    "created": "2025-01-16",
    "source": "[Semantic Gap Generative Dataset v5.0 – Fenomény / Situace / Kurátor] od Michaela Nováková"
  },
  {
    "id": "5.047",
    "text": "očekávání naruby, opice chyby nehledá tak nejsou, okázalost která sleduje sama sebe",
    "type": "psychologicko-sociální",
    "function": "zkoumá převrácená očekávání a sebestřednost",
    "fields": ["očekávání", "chyby", "opice", "okázalost"],
    "movement": "obrat → sebestřednost",
    "intensity": "střední",
    "language": "cs",
    "version": "1.0",
    "created": "2025-01-16",
    "source": "[Semantic Gap Generative Dataset v5.0 – Fenomény / Situace / Kurátor] od Michaela Nováková"
  },
  {
    "id": "5.048",
    "text": "překvapení z předvídatelného, imperativ samocenzury, identita vzniklá z nekonečného zrcadlení",
    "type": "psychologicko-filosofický",
    "function": "zkoumá paradox překvapení, cenzuru a reflexivní identitu",
    "fields": ["překvapení", "cenzura", "identita", "zrcadlení"],
    "movement": "paradox → reflexe",
    "intensity": "vysoká",
    "language": "cs",
    "version": "1.0",
    "created": "2025-01-16",
    "source": "[Semantic Gap Generative Dataset v5.0 – Fenomény / Situace / Kurátor] od Michaela Nováková"
  },
  {
    "id": "5.049",
    "text": "rytmus který mění vodu počítání jako tik detail který drží svět",
    "type": "metafyzicko-matematický",
    "function": "zkoumá rytmus jako sílu a detail jako oporu",
    "fields": ["rytmus", "voda", "počítání", "detail"],
    "movement": "rytmus → řád",
    "intensity": "střední",
    "language": "cs",
    "version": "1.0",
    "created": "2025-01-16",
    "source": "[Semantic Gap Generative Dataset v5.0 – Fenomény / Situace / Kurátor] od Michaela Nováková"
  },
  {
    "id": "5.050",
    "text": "skok skrz nemožné nemůžu to zastavit jen sledovat pozornost místo moci",
    "type": "existenciálně-politický",
    "function": "zkoumá skok do nemožna a pozornost jako alternativu moci",
    "fields": ["skok", "nemožné", "pozornost", "moc"],
    "movement": "akce → pasivita",
    "intensity": "vysoká",
    "language": "cs",
    "version": "1.0",
    "created": "2025-01-16",
    "source": "[Semantic Gap Generative Dataset v5.0 – Fenomény / Situace / Kurátor] od Michaela Nováková"
  }
]
